parquet_py-0.2.1b0.dist-info/METADATA
parquet_py-0.2.1b0.dist-info/WHEEL
parquet_py-0.2.1b0.dist-info/entry_points.txt
parquet_py-0.2.1b0.dist-info/license_files/LICENSE
parq/cli/__init__.py
parq/cli/__main__.py
parq/__init__.py
parq/lib.cp38-win_amd64.pyd
parquet_py-0.2.1b0.dist-info/RECORD
