Metadata-Version: 2.3
Name: parquet-py
Version: 0.2.1b0
Classifier: Programming Language :: Rust
Classifier: Programming Language :: Python :: Implementation :: CPython
Classifier: Programming Language :: Python :: Implementation :: PyPy
Requires-Dist: click >=7.0.0
License-File: LICENSE
Summary: A simple command-line interface & Python API for parquet
Home-Page: https://github.com/zachspar/parquet-py
Requires-Python: >=3.8
Project-URL: Source Code, https://github.com/zachspar/parquet-py.git
